my_api/__init__.py
my_api/urls.py
my_api/wsgi.py
my_api/rest/__init__.py
my_api/rest/models.py
my_api/rest/serializers.py
my_api/rest/views.py
my_api/rest/migrations/__init__.py
my_api/rest/tests/__init__.py
my_api/rest/tests/base.py
my_api/rest/tests/test_basic.py
my_api/rest/tests/test_project.py
my_api/settings/__init__.py
my_api/settings/common.py
my_api/settings/local.py
my_api/settings/production.py
my_api/settings/qa.py
drf_microservice-0.8.4.dist-info/LICENSE
drf_microservice-0.8.4.dist-info/METADATA
drf_microservice-0.8.4.dist-info/WHEEL
drf_microservice-0.8.4.dist-info/top_level.txt
drf_microservice-0.8.4.dist-info/RECORD
