Metadata-Version: 2.1
Name: drf-microservice
Version: 0.8.4
Summary: 
Home-page: http://github.com/alainivars/drf-microservice
Author: Alain IVARS
Author-email: alainivars@gmail.com
License: Apache License 2.0
Keywords: django rest auth registration rest-framework django-registration api docker cookiecuter tox pytest
Platform: UNKNOWN
Classifier: Development Status :: 2 - Pre-Alpha
Classifier: Framework :: Django :: 3.0
Classifier: Intended Audience :: Developers
Classifier: Intended Audience :: System Administrators
Classifier: Operating System :: OS Independent
Classifier: License :: OSI Approved :: Apache Software License
Classifier: Programming Language :: Python
Classifier: Programming Language :: Python :: 3
Classifier: Programming Language :: Python :: 3.6
Classifier: Programming Language :: Python :: 3.7
Classifier: Programming Language :: Python :: 3.8
Classifier: Topic :: Internet :: WWW/HTTP
Requires-Python: >=3.6.*, !=3.7.*, !=3.8.*
